npyosmium/__init__.py
npyosmium/_osmium.cp312-win_amd64.pyd
npyosmium/_osmium.pyi
npyosmium/bz2.dll
npyosmium/file_processor.py
npyosmium/geom.cp312-win_amd64.pyd
npyosmium/geom.pyi
npyosmium/helper.py
npyosmium/index.cp312-win_amd64.pyd
npyosmium/index.pyi
npyosmium/io.cp312-win_amd64.pyd
npyosmium/io.pyi
npyosmium/libexpat.dll
npyosmium/py.typed
npyosmium/simple_handler.py
npyosmium/version.py
npyosmium/zlib1.dll
npyosmium/area/__init__.py
npyosmium/area/_area.cp312-win_amd64.pyd
npyosmium/filter/__init__.py
npyosmium/filter/_filter.cp312-win_amd64.pyd
npyosmium/osm/__init__.py
npyosmium/osm/_osm.cp312-win_amd64.pyd
npyosmium/osm/_osm.pyi
npyosmium/osm/mutable.py
npyosmium/osm/types.py
npyosmium/replication/__init__.py
npyosmium/replication/_replication.cp312-win_amd64.pyd
npyosmium/replication/_replication.pyi
npyosmium/replication/bz2.dll
npyosmium/replication/libexpat.dll
npyosmium/replication/server.py
npyosmium/replication/utils.py
npyosmium/replication/zlib1.dll
npyosmium-3.7.0.data/scripts/npyosmium-get-changes
npyosmium-3.7.0.data/scripts/npyosmium-up-to-date
npyosmium-3.7.0.dist-info/LICENSE.TXT
npyosmium-3.7.0.dist-info/METADATA
npyosmium-3.7.0.dist-info/WHEEL
npyosmium-3.7.0.dist-info/top_level.txt
npyosmium-3.7.0.dist-info/RECORD
