Metadata-Version: 2.1
Name: npyosmium
Version: 3.7.0
Summary: Python bindings for libosmium, the data processing library for OSM data, with numpy interface
Home-page: https://github.com/agrenott/npyosmium
Download-URL: https://github.com/agrenott/npyosmium
Author: Sarah Hoffmann
Author-email: lonvia@denofr.de
Maintainer: Aurélien Grenotton
Maintainer-email: agrenott@gmail.com
License: BSD
Keywords: OSM,OpenStreetMap,Osmium
Classifier: Development Status :: 4 - Beta
Classifier: Intended Audience :: Developers
Classifier: License :: OSI Approved :: BSD License
Classifier: Programming Language :: Python :: 3.8
Classifier: Programming Language :: Python :: 3.9
Classifier: Programming Language :: Python :: 3.10
Classifier: Programming Language :: Python :: 3.11
Classifier: Programming Language :: Python :: 3.12
Classifier: Programming Language :: Python :: Implementation :: CPython
Classifier: Programming Language :: C++
Requires-Python: >=3.8
License-File: LICENSE.TXT
Requires-Dist: requests
Provides-Extra: tests
Requires-Dist: pytest ; extra == 'tests'
Requires-Dist: pytest-httpserver ; extra == 'tests'
Requires-Dist: werkzeug ; extra == 'tests'
